objectstore_client/__init__.py
objectstore_client/auth.py
objectstore_client/client.py
objectstore_client/metadata.py
objectstore_client/metrics.py
objectstore_client/py.typed
objectstore_client/scope.py
objectstore_client/utils.py
objectstore_client-0.0.15.dist-info/WHEEL
objectstore_client-0.0.15.dist-info/METADATA
objectstore_client-0.0.15.dist-info/RECORD
