Metadata-Version: 2.3
Name: objectstore-client
Version: 0.0.15
Summary: Client SDK for Objectstore, the Sentry object storage platform
Author: Sentry
Author-email: Sentry <oss@sentry.io>
License: # Functional Source License, Version 1.1, Apache 2.0 Future License
Requires-Dist: sentry-sdk>=2.42.1
Requires-Dist: urllib3>=2.2.2
Requires-Dist: zstandard>=0.18.0
Requires-Dist: filetype>=1.2.0
Requires-Dist: pyjwt[crypto]>=2.10.1
Requires-Python: >=3.11
